menuer/__init__.py
menuer/menuer.py
menuer-0.0.1.dist-info/METADATA
menuer-0.0.1.dist-info/WHEEL
menuer-0.0.1.dist-info/top_level.txt
menuer-0.0.1.dist-info/RECORD
