Metadata-Version: 2.1
Name: menuer
Version: 0.0.1
Summary: A basic menu generator
Home-page: UNKNOWN
Author: Ben Wilcken
Author-email: goast75@web.de
License: UNKNOWN
Keywords: python,menu,generator,terminal
Platform: UNKNOWN
Classifier: Development Status :: 1 - Planning
Classifier: Intended Audience :: Developers
Classifier: Programming Language :: Python :: 3
Classifier: Operating System :: Unix
Classifier: Operating System :: MacOS :: MacOS X
Classifier: Operating System :: Microsoft :: Windows
Requires-Dist: termcolor
Requires-Dist: pyfiglet
